design/priority_encoder.v
`timescale 1ns / 1ps

module priority_encoder (
    input  wire [7:0] req,
    output reg  [2:0] highest,
    output reg        any_req
);

    always @(*) begin
        any_req = 1'b1;
        if      (req[0]) highest = 3'd0;
        else if (req[1]) highest = 3'd1;
        else if (req[2]) highest = 3'd2;
        else if (req[3]) highest = 3'd3;
        else if (req[4]) highest = 3'd4;
        else if (req[5]) highest = 3'd5;
        else if (req[6]) highest = 3'd6;
        else if (req[7]) highest = 3'd7;
        else begin
            highest = 3'd0;
            any_req = 1'b0;
        end
    end

endmodule

design/programmable_pic.v
`timescale 1ns / 1ps

module programmable_pic (
    input  wire       clk,
    input  wire       rst,
    input  wire       cs,
    input  wire       wr,
    input  wire       rd,
    input  wire       a0,
    inout  wire [7:0] data_bus,
    output reg        int_req,
    input  wire       inta,
    input  wire [7:0] irq
);

    reg [7:0] irr;
    reg [7:0] isr;
    reg [7:0] imr;
    reg [7:0] base_vector;
    reg [7:0] data_out;
    reg       drive_bus;
    reg [7:0] irq_prev;

    wire [7:0] data_in = data_bus;
    assign data_bus = drive_bus ? data_out : 8'bz;

    wire [2:0] highest_irr;
    wire       any_irr;
    wire [7:0] active_req = irr & ~imr;

    priority_encoder pe_irr (
        .req(active_req),
        .highest(highest_irr),
        .any_req(any_irr)
    );

    wire [2:0] highest_isr;
    wire       any_isr;

    priority_encoder pe_isr (
        .req(isr),
        .highest(highest_isr),
        .any_req(any_isr)
    );

    always @(posedge clk or posedge rst) begin
        if (rst) begin
            irr         <= 8'd0;
            isr         <= 8'd0;
            imr         <= 8'hFF;
            base_vector <= 8'd0;
            irq_prev    <= 8'd0;
            int_req     <= 1'b0;
            drive_bus   <= 1'b0;
            data_out    <= 8'd0;
        end else begin
            irq_prev <= irq;
            irr <= irr | (irq & ~irq_prev);

            if (cs && wr) begin
                if (a0 == 1'b0) begin
                    if (data_in == 8'h20) begin
                        if (any_isr) isr[highest_isr] <= 1'b0;
                    end else begin
                        base_vector <= data_in;
                    end
                end else begin
                    imr <= data_in;
                end
            end

            if (inta) begin
                drive_bus <= 1'b1;
                if (any_irr) begin
                    data_out <= base_vector + {5'd0, highest_irr};
                    isr[highest_irr] <= 1'b1;
                    irr[highest_irr] <= 1'b0;
                end else begin
                    data_out <= 8'hFF;
                end
            end else if (cs && rd) begin
                drive_bus <= 1'b1;
                if (a0 == 1'b0) data_out <= irr;
                else            data_out <= imr;
            end else begin
                drive_bus <= 1'b0;
            end

            if (any_irr) begin
                if (!any_isr || (highest_irr < highest_isr)) begin
                    int_req <= 1'b1;
                end else begin
                    int_req <= 1'b0;
                end
            end else begin
                int_req <= 1'b0;
            end

            if (inta) int_req <= 1'b0;
        end
    end

endmodule

tb/tb_programmable_pic.v
`timescale 1ns / 1ps

module tb_programmable_pic;

    reg        clk;
    reg        rst;
    reg        cs;
    reg        wr;
    reg        rd;
    reg        a0;
    reg  [7:0] tb_data_out;
    reg        tb_drive_bus;
    wire [7:0] data_bus;
    wire       int_req;
    reg        inta;
    reg  [7:0] irq;

    assign data_bus = tb_drive_bus ? tb_data_out : 8'bz;

    programmable_pic dut (
        .clk(clk),
        .rst(rst),
        .cs(cs),
        .wr(wr),
        .rd(rd),
        .a0(a0),
        .data_bus(data_bus),
        .int_req(int_req),
        .inta(inta),
        .irq(irq)
    );

    initial clk = 0;
    always #5 clk = ~clk;

    task cpu_write;
        input reg target_a0;
        input reg [7:0] wdata;
        begin
            @(negedge clk);
            cs = 1; wr = 1; rd = 0; a0 = target_a0;
            tb_drive_bus = 1; tb_data_out = wdata;
            @(negedge clk);
            cs = 0; wr = 0; tb_drive_bus = 0;
        end
    endtask

    task cpu_ack;
        begin
            @(negedge clk);
            inta = 1;
            @(negedge clk);
            $display("CPU Received Vector: 0x%h", data_bus);
            inta = 0;
        end
    endtask

    initial begin
        // ***** DUMP WAVEFORM *****
        $dumpfile("wave.vcd");
        $dumpvars(0, tb_programmable_pic);

        // Testbench initialization and stimulus
        rst = 1; cs = 0; wr = 0; rd = 0; a0 = 0;
        tb_drive_bus = 0; tb_data_out = 8'd0;
        inta = 0; irq = 8'd0;

        #25 rst = 0;

        cpu_write(0, 8'h40);
        cpu_write(1, 8'h00);

        #30;

        repeat (10) begin
            #({$random} % 50 + 20);
            irq = $random;

            if (int_req) cpu_ack();

            #10;
            irq = 8'b00000000;

            if ({$random} % 2 == 0) begin
                cpu_write(0, 8'h20);
            end
        end

        #100 $finish;
    end

    initial begin
        $monitor("Time: %4t | IRQ: %b | INT_REQ: %b | INTA: %b | IRR: %b | ISR: %b | IMR: %b",
                 $time, irq, int_req, inta, dut.irr, dut.isr, dut.imr);
    end

endmodule

wave.vcd
$date
	Wed Apr 15 17:10:41 2026
$end
$version
	Icarus Verilog
$end
$timescale
	1ps
$end
$scope module tb_programmable_pic $end
$var wire 8 ! data_bus [7:0] $end
$var wire 1 " int_req $end
$var reg 1 # a0 $end
$var reg 1 $ clk $end
$var reg 1 % cs $end
$var reg 1 & inta $end
$var reg 8 ' irq [7:0] $end
$var reg 1 ( rd $end
$var reg 1 ) rst $end
$var reg 8 * tb_data_out [7:0] $end
$var reg 1 + tb_drive_bus $end
$var reg 1 , wr $end
$scope module dut $end
$var wire 1 # a0 $end
$var wire 8 - active_req [7:0] $end
$var wire 1 $ clk $end
$var wire 1 % cs $end
$var wire 8 . data_bus [7:0] $end
$var wire 8 / data_in [7:0] $end
$var wire 1 & inta $end
$var wire 8 0 irq [7:0] $end
$var wire 1 ( rd $end
$var wire 1 ) rst $end
$var wire 1 , wr $end
$var wire 3 1 highest_isr [2:0] $end
$var wire 3 2 highest_irr [2:0] $end
$var wire 1 3 any_isr $end
$var wire 1 4 any_irr $end
$var reg 8 5 base_vector [7:0] $end
$var reg 8 6 data_out [7:0] $end
$var reg 1 7 drive_bus $end
$var reg 8 8 imr [7:0] $end
$var reg 1 " int_req $end
$var reg 8 9 irq_prev [7:0] $end
$var reg 8 : irr [7:0] $end
$var reg 8 ; isr [7:0] $end
$scope module pe_irr $end
$var wire 8 < req [7:0] $end
$var reg 1 4 any_req $end
$var reg 3 = highest [2:0] $end
$upscope $end
$scope module pe_isr $end
$var wire 8 > req [7:0] $end
$var reg 1 3 any_req $end
$var reg 3 ? highest [2:0] $end
$upscope $end
$upscope $end
$scope task cpu_ack $end
$upscope $end
$scope task cpu_write $end
$var reg 1 @ target_a0 $end
$var reg 8 A wdata [7:0] $end
$upscope $end
$upscope $end
$enddefinitions $end
$comment Show the parameter values. $end
$dumpall
$end
#0
$dumpvars
bx A
x@
b0 ?
b0 >
b0 =
b0 <
b0 ;
b0 :
b0 9
b11111111 8
07
b0 6
b0 5
04
03
b0 2
b0 1
b0 0
bz /
bz .
b0 -
0,
0+
b0 *
1)
0(
b0 '
0&
0%
0$
0#
0"
bz !
$end
#5000
1$
#10000
0$
#15000
1$
#20000
0$
#25000
1$
b1000000 A
0@
0)
#30000
b1000000 /
b1000000 !
b1000000 .
b1000000 *
1+
1,
1%
0$
#35000
b1000000 5
1$
#40000
bz /
bz !
bz .
b0 A
1@
0+
0,
0%
0$
#45000
1$
#50000
b0 /
b0 !
b0 .
b0 *
1+
1#
1,
1%
0$
#55000
b0 8
1$
#60000
bz /
bz !
bz .
0+
0,
0%
0$
#65000
1$
#70000
0$
#75000
1$
#80000
0$
#85000
1$
#90000
0$
#95000
1$
#100000
0$
#105000
1$
#110000
0$
#115000
1$
#120000
0$
#125000
1$
#130000
0$
#135000
1$
#140000
0$
#145000
1$
#150000
0$
#155000
1$
#158000
b10000001 '
b10000001 0
#160000
0$
#165000
14
b10000001 -
b10000001 <
b10000001 :
b10000001 9
1$
#168000
b0 '
b0 0
#170000
0$
#175000
1"
b0 9
1$
#180000
0$
#185000
1$
#190000
0$
#195000
1$
#200000
0$
#205000
1$
#210000
0$
#215000
1$
#220000
0$
#225000
b10001101 -
b10001101 <
b10001101 :
b1101 9
1$
b1101 '
b1101 0
#230000
1&
0$
#235000
b10 2
b10 =
b10001100 -
b10001100 <
13
b1000000 /
b1000000 !
b1000000 .
0"
b10001100 :
b1 ;
b1 >
b1000000 6
17
1$
#240000
0&
0$
#245000
bz /
bz !
bz .
07
1$
#250000
0$
b0 '
b0 0
#255000
b0 9
1$
#260000
0$
#265000
1$
#270000
0$
#275000
1$
#280000
0$
#285000
1$
#290000
0$
#295000
b1 2
b1 =
b10011110 -
b10011110 <
b10011110 :
b10010 9
1$
b10010 '
b10010 0
#300000
0$
#305000
b0 9
1$
b0 '
b0 0
#310000
0$
#315000
1$
#320000
0$
#325000
1$
#330000
0$
#335000
1$
#340000
0$
#345000
1$
#350000
0$
#354000
b1110110 '
b1110110 0
#355000
b11111110 -
b11111110 <
b11111110 :
b1110110 9
1$
#360000
0$
#364000
b0 '
b0 0
#365000
b0 9
1$
#370000
0$
#375000
1$
#380000
0$
#385000
1$
#390000
0$
#395000
1$
#400000
0$
#405000
1$
#410000
0$
#413000
b10001100 '
b10001100 0
#415000
b10001100 9
1$
#420000
0$
#423000
b0 '
b0 0
#425000
b0 9
1$
#430000
0$
#435000
1$
#440000
0$
#445000
1$
#450000
0$
#455000
1$
#460000
0$
#465000
1$
#469000
b11000101 '
b11000101 0
#470000
0$
#475000
b0 2
b0 =
b11111111 -
b11111111 <
b11111111 :
b11000101 9
1$
#479000
b100000 A
0@
b0 '
b0 0
#480000
b100000 /
b100000 !
b100000 .
b100000 *
1+
0#
1,
1%
0$
#485000
03
b0 ;
b0 >
b0 9
1$
#490000
bz /
bz !
bz .
0+
0,
0%
0$
#495000
1"
1$
#500000
0$
#505000
1$
#510000
0$
#515000
1$
#520000
0$
#525000
1$
#530000
0$
#535000
1$
#540000
0$
#545000
b1110111 9
1$
b1110111 '
b1110111 0
#550000
1&
0$
#555000
b1 2
b1 =
b11111110 -
b11111110 <
13
b1000000 /
b1000000 !
b1000000 .
0"
b11111110 :
b1 ;
b1 >
17
1$
#560000
0&
0$
#565000
bz /
bz !
bz .
07
1$
#570000
b100000 /
b100000 !
b100000 .
1+
1,
1%
0$
b0 '
b0 0
#575000
03
b0 ;
b0 >
b0 9
1$
#580000
bz /
bz !
bz .
0+
0,
0%
0$
#585000
1"
1$
#590000
0$
#595000
1$
#600000
0$
#605000
1$
#610000
0$
#615000
1$
#620000
0$
#625000
1$
#630000
0$
#635000
1$
#639000
b11110010 '
b11110010 0
#640000
1&
0$
#645000
b10 2
b10 =
b11111100 -
b11111100 <
b1 1
b1 ?
13
b1000001 /
b1000001 !
b1000001 .
0"
b11111100 :
b10 ;
b10 >
b1000001 6
17
b11110010 9
1$
#650000
0&
0$
#655000
bz /
bz !
bz .
07
1$
#660000
b100000 /
b100000 !
b100000 .
1+
1,
1%
0$
b0 '
b0 0
#665000
03
b0 1
b0 ?
b0 ;
b0 >
b0 9
1$
#670000
bz /
bz !
bz .
0+
0,
0%
0$
#675000
1"
1$
#680000
0$
#685000
1$
#690000
0$
#695000
1$
#700000
0$
#705000
1$
#708000
b11000101 '
b11000101 0
#710000
1&
0$
#715000
b0 2
b0 =
b10 1
b10 ?
13
b1000010 /
b1000010 !
b1000010 .
b11111001 -
b11111001 <
0"
b100 ;
b100 >
b1000010 6
17
b11111001 :
b11000101 9
1$
#720000
0&
0$
#725000
bz /
bz !
bz .
1"
07
1$
#730000
b100000 /
b100000 !
b100000 .
1+
1,
1%
0$
b0 '
b0 0
#735000
03
b0 1
b0 ?
b0 ;
b0 >
b0 9
1$
#740000
bz /
bz !
bz .
0+
0,
0%
0$
#745000
1$
#750000
0$
#755000
1$
#760000
0$
#765000
1$
#770000
0$
#775000
1$
#780000
0$
#785000
1$
#790000
0$
#795000
1$
#800000
0$
#803000
b101101 '
b101101 0
#805000
b11111101 -
b11111101 <
b11111101 :
b101101 9
1$
#810000
1&
0$
#815000
b10 2
b10 =
b11111100 -
b11111100 <
13
b1000000 /
b1000000 !
b1000000 .
0"
b11111100 :
b1 ;
b1 >
b1000000 6
17
1$
#820000
0&
0$
#825000
bz /
bz !
bz .
07
1$
#830000
0$
b0 '
b0 0
#835000
b0 9
1$
